pyllab.cp37-win_amd64.pyd
Pyllab-1.0.2.dist-info/LICENSE
Pyllab-1.0.2.dist-info/METADATA
Pyllab-1.0.2.dist-info/WHEEL
Pyllab-1.0.2.dist-info/top_level.txt
Pyllab-1.0.2.dist-info/RECORD
