Metadata-Version: 2.1
Name: Pyllab
Version: 1.0.2
Summary: Deep learning library
Home-page: https://github.com/ez-spark/Pyllab
Author: Riccardo Viviano, Matteo Galdi
Author-email: riccardoviviano@gmail.com
License: UNKNOWN
Platform: UNKNOWN
License-File: LICENSE
